{
  "id": "524fa4eb-2234-41fd-9940-dc734afc309b",
  "prevId": "00000000-0000-0000-0000-000000000000",
  "version": "7",
  "dialect": "postgresql",
  "tables": {
    "public.links": {
      "name": "links",
      "schema": "",
      "columns": {
        "id": {
          "name": "id",
          "type": "text",
          "primaryKey": true,
          "notNull": true
        },
        "original_link": {
          "name": "original_link",
          "type": "text",
          "primaryKey": false,
          "notNull": true
        },
        "short_link": {
          "name": "short_link",
          "type": "text",
          "primaryKey": false,
          "notNull": true
        },
        "access_count": {
          "name": "access_count",
          "type": "integer",
          "primaryKey": false,
          "notNull": true,
          "default": 0
        },
        "created_at": {
          "name": "created_at",
          "type": "timestamp",
          "primaryKey": false,
          "notNull": false,
          "default": "now()"
        }
      },
      "indexes": {},
      "foreignKeys": {},
      "compositePrimaryKeys": {},
      "uniqueConstraints": {
        "links_short_link_unique": {
          "name": "links_short_link_unique",
          "nullsNotDistinct": false,
          "columns": [
            "short_link"
          ]
        }
      },
      "policies": {},
      "checkConstraints": {},
      "isRLSEnabled": false
    }
  },
  "enums": {},
  "schemas": {},
  "sequences": {},
  "roles": {},
  "policies": {},
  "views": {},
  "_meta": {
    "columns": {},
    "schemas": {},
    "tables": {}
  }
}